{
    "/js/app.js": "/js/app.js",
    "/css/app.css": "/css/app.css",
    "/js/app.a39a6a96ee3928b888c4.hot-update.js": "/js/app.a39a6a96ee3928b888c4.hot-update.js",
    "/js/app.90298ada377fd232e9bc.hot-update.js": "/js/app.90298ada377fd232e9bc.hot-update.js",
    "/js/app.6a306c7a341646c8bfe9.hot-update.js": "/js/app.6a306c7a341646c8bfe9.hot-update.js",
    "/js/app.39cd4cfb6ce90ae3fe30.hot-update.js": "/js/app.39cd4cfb6ce90ae3fe30.hot-update.js",
    "/js/app.7e39143fc0299f006a4a.hot-update.js": "/js/app.7e39143fc0299f006a4a.hot-update.js",
    "/js/app.99f1c96f210afc562e13.hot-update.js": "/js/app.99f1c96f210afc562e13.hot-update.js",
    "/js/app.78d85e92187aafef852a.hot-update.js": "/js/app.78d85e92187aafef852a.hot-update.js",
    "/js/app.d018184034f16e6a37ab.hot-update.js": "/js/app.d018184034f16e6a37ab.hot-update.js",
    "/js/app.b75be4655e79b0778dd7.hot-update.js": "/js/app.b75be4655e79b0778dd7.hot-update.js",
    "/js/app.59a10a69e2004aca2e24.hot-update.js": "/js/app.59a10a69e2004aca2e24.hot-update.js"
}
